[
  {
    "news": "Lorem ipsum dolor sit amet, consectetur adipiscing elit." },
  { "news": "Pellentesque habitant morbi tristique senectus et netus et malesuada fames ac turpis egestas." },
  { "news": "Vestibulum nec sapien vel nunc dignissim sagittis." },
  { "news": "Pellentesque habitant morbi tristique senectus et netus et malesuada fames ac turpis egestas." },
  { "news": "Pellentesque habitant morbi tristique senectus et netus et malesuada fames ac turpis egestas." },
  { "news": "Vestibulum nec sapien vel nunc dignissim sagittis." },
  { "news": "Pellentesque habitant morbi tristique senectus et netus et malesuada fames ac turpis egestas." },
  { "news": "Vestibulum nec sapien vel nunc dignissim sagittis." },
  { "news": "Vestibulum nec sapien vel nunc dignissim sagittis." },
  { "news": "Aliquam erat volutpat. Proin ut nunc at libero tempor tristique." }
]
